kore/__init__.py
kore/components/__init__.py
kore/components/factories.py
kore/components/registrars.py
kore/components/signals.py
kore/components/plugins/__init__.py
kore/components/plugins/base.py
kore/configs/__init__.py
kore/configs/exceptions.py
kore/configs/factories.py
kore/configs/models.py
kore/configs/plugins/__init__.py
kore/configs/plugins/base.py
kore/configs/plugins/dict.py
kore/containers/__init__.py
kore/containers/factories.py
kore/containers/models.py
kore/containers/signals.py
kore/plugins/__init__.py
kore/plugins/exceptions.py
kore/plugins/iterators.py
kore/plugins/models.py
kore/plugins/providers.py
kore-0.1.0.dist-info/DESCRIPTION.rst
kore-0.1.0.dist-info/METADATA
kore-0.1.0.dist-info/RECORD
kore-0.1.0.dist-info/WHEEL
kore-0.1.0.dist-info/entry_points.txt
kore-0.1.0.dist-info/metadata.json
kore-0.1.0.dist-info/top_level.txt
