Metadata-Version: 2.0
Name: kore
Version: 0.1.0
Summary: UNKNOWN
Home-page: https://github.com/p1c2u/kore
Author: Artur Maciąg
Author-email: maciag.artur@gmail.com
License: UNKNOWN
Platform: UNKNOWN
Classifier: Intended Audience :: Developers
Classifier: Programming Language :: Python :: 2.7
Classifier: Programming Language :: Python :: 3.4
Classifier: Programming Language :: Python :: 3.6
Classifier: Topic :: Software Development :: Libraries
Requires-Dist: blinker (==1.4)
Requires-Dist: knot (==0.4.0)
